CMakeLists.txt
LICENSE
MANIFEST.in
README.md
pyproject.toml
requirements.txt
setup.py
capi/py.typed
capi/cpp_libs/catch2/catch.cpp
capi/cpp_libs/catch2/catch.hpp
capi/cpp_libs/fmt/include/fmt/chrono.h
capi/cpp_libs/fmt/include/fmt/color.h
capi/cpp_libs/fmt/include/fmt/compile.h
capi/cpp_libs/fmt/include/fmt/core.h
capi/cpp_libs/fmt/include/fmt/format-inl.h
capi/cpp_libs/fmt/include/fmt/format.h
capi/cpp_libs/fmt/include/fmt/locale.h
capi/cpp_libs/fmt/include/fmt/os.h
capi/cpp_libs/fmt/include/fmt/ostream.h
capi/cpp_libs/fmt/include/fmt/posix.h
capi/cpp_libs/fmt/include/fmt/printf.h
capi/cpp_libs/fmt/include/fmt/ranges.h
capi/cpp_libs/fmt/src/format.cc
capi/cpp_libs/fmt/src/os.cc
capi/cpp_libs/indicators/include/indicators/block_progress_bar.hpp
capi/cpp_libs/indicators/include/indicators/color.hpp
capi/cpp_libs/indicators/include/indicators/cursor_control.hpp
capi/cpp_libs/indicators/include/indicators/cursor_movement.hpp
capi/cpp_libs/indicators/include/indicators/display_width.hpp
capi/cpp_libs/indicators/include/indicators/dynamic_progress.hpp
capi/cpp_libs/indicators/include/indicators/font_style.hpp
capi/cpp_libs/indicators/include/indicators/indeterminate_progress_bar.hpp
capi/cpp_libs/indicators/include/indicators/multi_progress.hpp
capi/cpp_libs/indicators/include/indicators/progress_bar.hpp
capi/cpp_libs/indicators/include/indicators/progress_spinner.hpp
capi/cpp_libs/indicators/include/indicators/progress_type.hpp
capi/cpp_libs/indicators/include/indicators/setting.hpp
capi/cpp_libs/indicators/include/indicators/termcolor.hpp
capi/cpp_libs/indicators/include/indicators/terminal_size.hpp
capi/cpp_libs/indicators/include/indicators/details/stream_helper.hpp
capi/cpp_libs/mio/mio.hpp
capi/src/hypothesis_strategies/__init__.py
capi/src/hypothesis_strategies/coordinate.py
capi/src/hypothesis_strategies/polygon.py
capi/src/implementation/__init__.py
capi/src/implementation/graph_generator.py
capi/src/implementation/graph_merger.py
capi_vis.egg-info/PKG-INFO
capi_vis.egg-info/SOURCES.txt
capi_vis.egg-info/dependency_links.txt
capi_vis.egg-info/not-zip-safe
capi_vis.egg-info/requires.txt
capi_vis.egg-info/top_level.txt
