Metadata-Version: 2.1
Name: capi-vis
Version: 3.0.3
Summary: Python library for performing coast aware path interpolation using visibility graphs
Home-page: https://github.com/Balajanovski/capi
Author: James Balajan
Author-email: James.Balajan@wisetechglobal.com
License: UNKNOWN
Platform: UNKNOWN
Classifier: Programming Language :: Python :: 3
Classifier: Operating System :: OS Independent
Requires-Python: >=3.6
License-File: LICENSE
